{"metadata":{"asset_id":"c3c6e1e8-5e0f-42b8-8de5-b91d3d0c9d00","asset_attributes":["job"],"name":"First-nb-job","asset_type":"job","created_at":"2021-01-26T04:39:05Z","description":"","origin_country":"us","owner_id":"1000330999","project_id":"cdc0bb92-6822-4937-8ab2-eff704c5d515","size":0,"tags":[],"usage":{"last_update_time":1611635945662,"last_updated_at":"2021-01-26T04:39:05Z"}},"entity":{"job":{"asset_ref_type":"notebook","configuration":{"env_id":"jupconda37-cdc0bb92-6822-4937-8ab2-eff704c5d515","version":"79703896-0c5c-4dee-821b-b85c764940a3","env_type":"notebook","env_variables":[]},"schedule":"0 5 26 1 *","schedule_info":{"startOn":1611637200000,"repeat":false},"last_run_initiator":"None","last_run_time":"","last_run_status":"None","last_run_status_timestamp":0,"project_name":"R-Shiny-App-Test","asset_ref":"56923971-04ae-4f03-9854-4b1b253d25ab"}}}